MANIFEST.in
README.rst
setup.py
assetmanager/__init__.py
assetmanager/admin.py
assetmanager/apps.py
assetmanager/forms.py
assetmanager/models.py
assetmanager/serializers.py
assetmanager/settings.py
assetmanager/tests.py
assetmanager/views.py
assetmanager/migrations/__init__.py
assetmanager/static/assetmanager/admin/css/asset_list.css
assetmanager/static/assetmanager/admin/css/fontello/LICENSE.txt
assetmanager/static/assetmanager/admin/css/fontello/README.txt
assetmanager/static/assetmanager/admin/css/fontello/config.json
assetmanager/static/assetmanager/admin/css/fontello/demo.html
assetmanager/static/assetmanager/admin/css/fontello/css/animation.css
assetmanager/static/assetmanager/admin/css/fontello/css/fontello-codes.css
assetmanager/static/assetmanager/admin/css/fontello/css/fontello-embedded.css
assetmanager/static/assetmanager/admin/css/fontello/css/fontello-ie7-codes.css
assetmanager/static/assetmanager/admin/css/fontello/css/fontello-ie7.css
assetmanager/static/assetmanager/admin/css/fontello/css/fontello.css
assetmanager/static/assetmanager/admin/css/fontello/font/fontello.eot
assetmanager/static/assetmanager/admin/css/fontello/font/fontello.svg
assetmanager/static/assetmanager/admin/css/fontello/font/fontello.ttf
assetmanager/static/assetmanager/admin/css/fontello/font/fontello.woff
assetmanager/static/assetmanager/admin/js/asset_list.js
assetmanager/templates/asset_list.html
assetmanager/templates/asset_view.html
assetmanager/templates/asset_widget.html
assetmanager/templatetags/__init__.py
assetmanager/templatetags/assetmanager_extras.py
fh_django_assetmanager.egg-info/PKG-INFO
fh_django_assetmanager.egg-info/SOURCES.txt
fh_django_assetmanager.egg-info/dependency_links.txt
fh_django_assetmanager.egg-info/requires.txt
fh_django_assetmanager.egg-info/top_level.txt