Metadata-Version: 1.0
Name: fh-django-assetmanager
Version: 0.2.10
Summary: Django asset manager providing search (MySQL) and custom file field to use in models.
Home-page: https://gitlab.com/futurehaus/django-assetmanager
Author: UNKNOWN
Author-email: UNKNOWN
License: UNKNOWN
Platform: UNKNOWN
